Metadata-Version: 2.1
Name: gwaspy
Version: 0.1.1
Summary: GWASpy: A Python package for performing GWAS QC, PCA, phasing, and genotype imputation.
Home-page: https://gwaspy.readthedocs.io/
Author: Lindokuhle Nkambule
Author-email: lnkambul@broadinstitute.org
License: MIT
Project-URL: GitHub, https://github.com/atgu/GWASpy
Classifier: Development Status :: 4 - Beta
Classifier: Environment :: Console
Classifier: Intended Audience :: Science/Research
Classifier: License :: OSI Approved :: MIT License
Classifier: Programming Language :: Python :: 3
Classifier: Programming Language :: Python :: 3.2
Classifier: Programming Language :: Python :: 3.3
Classifier: Programming Language :: Python :: 3.4
Classifier: Programming Language :: Python :: 3.5
Classifier: Programming Language :: Python :: 3.6
Classifier: Programming Language :: Python :: 3.7
Classifier: Programming Language :: Python :: 3.8
Classifier: Topic :: Scientific/Engineering :: Bio-Informatics
Classifier: Operating System :: POSIX
Classifier: Operating System :: Unix
Classifier: Operating System :: MacOS
License-File: LICENSE
Requires-Dist: hail
Requires-Dist: matplotlib
Requires-Dist: numpy
Requires-Dist: pandas
Requires-Dist: pylatex
Requires-Dist: plotly
